properly_model_python/__init__.py
properly_model_python/util.py
properly_model_python/alert_models/__init__.py
properly_model_python/alert_models/util.py
properly_model_python/alert_models/models/__init__.py
properly_model_python/alert_models/models/alert_notification.py
properly_model_python/alert_models/models/base_model_.py
properly_model_python/alert_models/models/lat_lng.py
properly_model_python/alert_models/models/lat_lng_bounds.py
properly_model_python/alert_models/models/person.py
properly_model_python/alert_models/models/search.py
properly_model_python/alert_models/models/search_notification.py
properly_model_python/alert_models/models/search_result.py
properly_model_python/alert_models/models/simple_listing.py
properly_model_python/alert_models/models/users_alert.py
properly_model_python/alert_models/models/users_recommendation.py
properly_model_python/alert_models/models/users_search.py
properly_model_python/favourite_models/__init__.py
properly_model_python/favourite_models/models/__init__.py
properly_model_python/favourite_models/models/base_model_.py
properly_model_python/favourite_models/models/listing_favourites.py
properly_model_python/favourite_models/models/listing_favourites_audit_log.py
properly_model_python/favourite_models/models/user_favourites.py
properly_model_python/models/__init__.py
properly_model_python/models/base_model_.py
properly_model_python/models/custom_annotation.py
properly_model_python/models/image.py
properly_model_python/models/listing_property.py
properly_model_python/models/model_property.py
properly_model_python/models/room.py
properly_model_python/models/sold_property.py
properly_model_python/search_models/__init__.py
properly_model_python/search_models/util.py
properly_model_python/search_models/models/__init__.py
properly_model_python/search_models/models/base_model_.py
properly_model_python/search_models/models/lat_lng.py
properly_model_python/search_models/models/lat_lng_bounds.py
properly_model_python-1.0.260.dist-info/METADATA
properly_model_python-1.0.260.dist-info/WHEEL
properly_model_python-1.0.260.dist-info/top_level.txt
properly_model_python-1.0.260.dist-info/RECORD
