Metadata-Version: 2.1
Name: properly_model_python
Version: 1.0.260
Summary: Models for common Properly operations in python.
Home-page: https://github.com/GoProperly/properly-model-python
Author: GoProperly
Author-email: info@goproperly.com
License: UNKNOWN
Platform: UNKNOWN
Classifier: Programming Language :: Python :: 3
